configurik/__init__.py
configurik/__init__.pyi
configurik-1.3.1.dist-info/LICENSE
configurik-1.3.1.dist-info/METADATA
configurik-1.3.1.dist-info/WHEEL
configurik-1.3.1.dist-info/top_level.txt
configurik-1.3.1.dist-info/RECORD
