Metadata-Version: 2.1
Name: configurik
Version: 1.3.1
Summary: Library for loading yml configurations
Home-page: https://github.com/Senopiece/python-config
Author: Vitaly Mahonin
Author-email: nabuki@vk.com
Requires-Python: >=3.8
License-File: LICENSE
Requires-Dist: python-dotenv<2.0.0,>=1.0.1
Requires-Dist: PyYAML<7.0.0,>=6.0.1
